{"bg_intro.md":"abc3cc6d","bg_modules_academic-structure-module.md":"a2716523","bg_modules_dashboard-module.md":"b4a2ec1c","bg_modules_grading-module.md":"7e88c2d0","bg_modules_user-management-module.md":"75a834cd","bg_setup_config.md":"1b2892d5","bg_setup_deployment-dev.md":"6e8402ad","bg_setup_deployment-prod.md":"06ebaaff","bg_setup_getting-started.md":"f70cce62","bg_setup_troubleshooting.md":"e15da214","en_intro.md":"43f784dd","en_modules_academic-structure-module.md":"36db0cc5","en_modules_dashboard-module.md":"fdbc636c","en_modules_grading-module.md":"4feef319","en_modules_user-management-module.md":"cba87dc6","en_setup_config.md":"4b33f8d1","en_setup_deployment-dev.md":"5410ab00","en_setup_deployment-prod.md":"f05cb493","en_setup_getting-started.md":"51575bfa","en_setup_troubleshooting.md":"ed0feba5","index.md":"8b060e0e"}
